{"entities":{"f7088277-d45f-46cd-9e5b-935928058d06":{"enabled":true,"tags":[],"children":["ae320b93-4347-4b4e-9eb3-fb55b4836967"],"position":[0,0,0],"rotation":[0,0,0],"scale":[1,1,1],"resource_id":"f7088277-d45f-46cd-9e5b-935928058d06","name":"RootNode","components":{},"parent":null},"ae320b93-4347-4b4e-9eb3-fb55b4836967":{"enabled":true,"tags":[],"children":[],"position":[0,2.16844,0],"rotation":[-180,0,180],"scale":[0.01,0.01,0.01],"resource_id":"ae320b93-4347-4b4e-9eb3-fb55b4836967","name":"brick_wall_large_corner","components":{"render":{"enabled":true,"type":"asset","asset":198313697,"materialAssets":[198313699,198313656,198313660],"layers":[0],"batchGroupId":null,"castShadows":true,"castShadowsLightmap":true,"receiveShadows":true,"lightmapped":false,"lightmapSizeMultiplier":1,"castShadowsLightMap":true,"lightMapped":false,"lightMapSizeMultiplier":1,"isStatic":false,"rootBone":null}},"parent":"f7088277-d45f-46cd-9e5b-935928058d06"}}}